MNIST_dir/__init__.py
MNIST_dir-0.1.dist-info/LICENSE.txt
MNIST_dir-0.1.dist-info/METADATA
MNIST_dir-0.1.dist-info/WHEEL
MNIST_dir-0.1.dist-info/top_level.txt
MNIST_dir-0.1.dist-info/RECORD
