Metadata-Version: 2.1
Name: MNIST_dir
Version: 0.1
Summary: MNIST dataset.
Home-page: https://github.com/JunzePeng/MNIST
Author: JunzePeng
Author-email: gxp@bupt.edu.cn
License: MIT
Classifier: License :: OSI Approved :: MIT License
Classifier: Programming Language :: Python :: 3
Classifier: Operating System :: OS Independent
Requires-Python: >=3.0.0
License-File: LICENSE.txt
